nvidia_tao_tf2/__init__.py
nvidia_tao_tf2/version.py
nvidia_tao_tf2/backbones/__init__.py
nvidia_tao_tf2/backbones/efficientnet_tf.py
nvidia_tao_tf2/backbones/mobilenet_tf.py
nvidia_tao_tf2/backbones/resnet_tf.py
nvidia_tao_tf2/backbones/utils_tf.py
nvidia_tao_tf2/blocks/__init__.py
nvidia_tao_tf2/blocks/pruner.py
nvidia_tao_tf2/blocks/trainer.py
nvidia_tao_tf2/blocks/dataloader/__init__.py
nvidia_tao_tf2/blocks/dataloader/dataset.py
nvidia_tao_tf2/blocks/processor/__init__.py
nvidia_tao_tf2/blocks/processor/postprocessor.py
nvidia_tao_tf2/blocks/processor/preprocessor.py
nvidia_tao_tf2/common/__init__.py
nvidia_tao_tf2/common/decorators.py
nvidia_tao_tf2/common/no_warning.py
nvidia_tao_tf2/common/utils.py
nvidia_tao_tf2/common/config/__init__.py
nvidia_tao_tf2/common/config/mlops.py
nvidia_tao_tf2/common/dataset/__init__.py
nvidia_tao_tf2/common/dataset/dataset_util.py
nvidia_tao_tf2/common/dataset/label_map_util.py
nvidia_tao_tf2/common/entrypoint/__init__.py
nvidia_tao_tf2/common/entrypoint/download_specs.py
nvidia_tao_tf2/common/entrypoint/entrypoint.py
nvidia_tao_tf2/common/hydra/__init__.py
nvidia_tao_tf2/common/hydra/hydra_runner.py
nvidia_tao_tf2/common/logging/__init__.py
nvidia_tao_tf2/common/logging/logging.py
nvidia_tao_tf2/common/mlops/__init__.py
nvidia_tao_tf2/common/mlops/clearml.py
nvidia_tao_tf2/common/mlops/utils.py
nvidia_tao_tf2/common/mlops/wandb.py
nvidia_tao_tf2/common/telemetry/__init__.py
nvidia_tao_tf2/common/telemetry/nvml_utils.py
nvidia_tao_tf2/common/telemetry/telemetry.py
nvidia_tao_tf2/cv/__init__.py
nvidia_tao_tf2/cv/classification/__init__.py
nvidia_tao_tf2/cv/classification/callback/__init__.py
nvidia_tao_tf2/cv/classification/callback/eff_checkpoint.py
nvidia_tao_tf2/cv/classification/config/__init__.py
nvidia_tao_tf2/cv/classification/config/default_config.py
nvidia_tao_tf2/cv/classification/entrypoint/__init__.py
nvidia_tao_tf2/cv/classification/entrypoint/classification.py
nvidia_tao_tf2-4.0.0.dist-info/LICENSE
nvidia_tao_tf2-4.0.0.dist-info/METADATA
nvidia_tao_tf2-4.0.0.dist-info/WHEEL
nvidia_tao_tf2-4.0.0.dist-info/entry_points.txt
nvidia_tao_tf2-4.0.0.dist-info/top_level.txt
nvidia_tao_tf2-4.0.0.dist-info/RECORD
